tower_defense/LICENSE
tower_defense/__init__.py
tower_defense/__main__.py
tower_defense/constants.py
tower_defense/discounts.py
tower_defense/functions.py
tower_defense/main.py
tower_defense/maps.py
tower_defense/powerups.py
tower_defense/resources/anti_camo_power_up.png
tower_defense/resources/banana_farm.png
tower_defense/resources/blood_rune.png
tower_defense/resources/bomb_tower.png
tower_defense/resources/bowler.png
tower_defense/resources/elemental.png
tower_defense/resources/explosion-0.png
tower_defense/resources/explosion-1.png
tower_defense/resources/explosion-2.png
tower_defense/resources/explosion.png
tower_defense/resources/explosion_rune.png
tower_defense/resources/fonts/UbuntuMono-Regular.ttf
tower_defense/resources/freeze_power_up.png
tower_defense/resources/gold_rune.png
tower_defense/resources/heal_power_up.png
tower_defense/resources/heart_0.png
tower_defense/resources/heart_1.png
tower_defense/resources/ice_circle.png
tower_defense/resources/ice_rune.png
tower_defense/resources/ice_tower.png
tower_defense/resources/icon.png
tower_defense/resources/inactive_inferno.png
tower_defense/resources/inferno.png
tower_defense/resources/leap_rune.png
tower_defense/resources/lightning_power_up.png
tower_defense/resources/lightning_rune.png
tower_defense/resources/rainbow_rune.png
tower_defense/resources/range.png
tower_defense/resources/reload_power_up.png
tower_defense/resources/rune.png
tower_defense/resources/shrink_rune.png
tower_defense/resources/skins/BAD.png
tower_defense/resources/skins/BFB.png
tower_defense/resources/skins/DDT.png
tower_defense/resources/skins/MOAB.png
tower_defense/resources/skins/ZOMG.png
tower_defense/resources/skins/christmas_banana_farm.png
tower_defense/resources/skins/christmas_bomb_tower.png
tower_defense/resources/skins/christmas_bowler.png
tower_defense/resources/skins/christmas_elemental.png
tower_defense/resources/skins/christmas_ice_tower.png
tower_defense/resources/skins/christmas_inactive_inferno.png
tower_defense-3.9.2.dist-info/entry_points.txt
tower_defense-3.9.2.dist-info/WHEEL
tower_defense-3.9.2.dist-info/METADATA
tower_defense-3.9.2.dist-info/RECORD
