Metadata-Version: 2.1
Name: tower-defense
Version: 3.9.2
Summary: 
Author: Ying Liqian
Author-email: jamesylq@gmail.com
Requires-Python: >=3.6,<4.0
Classifier: Programming Language :: Python :: 3
Classifier: Programming Language :: Python :: 3.6
Classifier: Programming Language :: Python :: 3.7
Classifier: Programming Language :: Python :: 3.8
Classifier: Programming Language :: Python :: 3.9
Requires-Dist: pygame (>=2.0.1,<3.0.0)
Requires-Dist: pyperclip (>=1.8.2,<2.0.0)
Requires-Dist: pytz (>=2021.3,<2022.0)
